data/__init__.py
data/combine_gold.py
data/download_latest_ror.py
data/ner_model/__init__.py
s2aff/__init__.py
s2aff/consts.py
s2aff/data.py
s2aff/features.py
s2aff/file_cache.py
s2aff/lightgbm_helpers.py
s2aff/model.py
s2aff/ror.py
s2aff/text.py
s2aff/timo/__init__.py
s2aff/timo/integration_test.py
s2aff/timo/interface.py
scripts/__init__.py
scripts/approximate_runtime_and_memory_usage.py
scripts/evaluate_first_stage_ranker.py
scripts/generate_lightgbm_training_data.py
scripts/train_lightgbm_reranker.py
scripts/train_ner_model.py
scripts/update_openalex_works_counts.py
s2aff-0.61.dist-info/LICENSE
s2aff-0.61.dist-info/METADATA
s2aff-0.61.dist-info/WHEEL
s2aff-0.61.dist-info/top_level.txt
s2aff-0.61.dist-info/RECORD
