Metadata-Version: 2.1
Name: s2aff
Version: 0.61
Summary: Semantic Scholar's Affiliation Extraction: Link Your Raw Affiliations to ROR IDs
Home-page: https://github.com/allenai/S2AFF
License-File: LICENSE
Requires-Dist: cmake
Requires-Dist: numpy
Requires-Dist: scipy
Requires-Dist: pandas (>=1.3)
Requires-Dist: blingfire
Requires-Dist: scikit-learn
Requires-Dist: text-unidecode
Requires-Dist: simpletransformers
Requires-Dist: awscli
Requires-Dist: boto3
Requires-Dist: nltk
Requires-Dist: pypi-kenlm
Requires-Dist: hyperopt
Requires-Dist: lightgbm
Requires-Dist: torch
Requires-Dist: pydantic
Requires-Dist: pytest
